pre_commit_hooks/__init__.py
pre_commit_hooks/remove_core_settings_tsproj.py
tc_prcmmt_hks-1.0.3.dist-info/licenses/LICENSE
tc_prcmmt_hks-1.0.3.dist-info/METADATA
tc_prcmmt_hks-1.0.3.dist-info/WHEEL
tc_prcmmt_hks-1.0.3.dist-info/entry_points.txt
tc_prcmmt_hks-1.0.3.dist-info/top_level.txt
tc_prcmmt_hks-1.0.3.dist-info/RECORD
