Metadata-Version: 2.4
Name: tc-prcmmt-hks
Version: 1.0.3
Summary: Reusable pre‑commit hooks for TwinCAT projects
Author-email: Jan B <jan.birkhofer@bluewin.ch>
License-Expression: MIT
Requires-Python: >=3.8
License-File: LICENSE
Dynamic: license-file
